setup.py
scratchy/__init__.py
scratchy.egg-info/PKG-INFO
scratchy.egg-info/SOURCES.txt
scratchy.egg-info/dependency_links.txt
scratchy.egg-info/not-zip-safe
scratchy.egg-info/top_level.txt