Metadata-Version: 1.0
Name: scratchy
Version: 0.1
Summary: A static site generator, aimed for blogging
Home-page: http://github.com/rizaldim/scratchy
Author: Rizaldi Martaputra
Author-email: rizaldi.m@gmail.com
License: MIT
Platform: UNKNOWN
